intrabus/__init__.py
intrabus/brokers.py
intrabus/bus_interface.py
intrabus/config.py
intrabus-0.1.0.dist-info/LICENSE
intrabus-0.1.0.dist-info/METADATA
intrabus-0.1.0.dist-info/WHEEL
intrabus-0.1.0.dist-info/RECORD
