Metadata-Version: 2.3
Name: intrabus
Version: 0.1.0
Summary: Lightweight ZeroMQ pub/sub + req/rep message bus for single‑host threaded / multi‑process Python apps
License: MIT
Keywords: zeromq,pubsub,rpc,message-bus,threading
Author: BuilderCrafter
Requires-Python: >=3.9,<4.0
Classifier: License :: OSI Approved :: MIT License
Classifier: Programming Language :: Python :: 3
Classifier: Programming Language :: Python :: 3.9
Classifier: Programming Language :: Python :: 3.10
Classifier: Programming Language :: Python :: 3.11
Classifier: Programming Language :: Python :: 3.12
Classifier: Programming Language :: Python :: 3.13
Requires-Dist: pyzmq (>=26.0,<27.0)
Project-URL: Repository, https://github.com/BuilderCrafter/intrabus
